gocept.pseudonymize-3.0-py3.11-nspkg.pth
gocept/pseudonymize/__init__.py
gocept/pseudonymize/pseudonymize.py
gocept/pseudonymize/tests/__init__.py
gocept/pseudonymize/tests/test_pseudonymize.py
gocept.pseudonymize-3.0.dist-info/LICENSE.txt
gocept.pseudonymize-3.0.dist-info/METADATA
gocept.pseudonymize-3.0.dist-info/WHEEL
gocept.pseudonymize-3.0.dist-info/namespace_packages.txt
gocept.pseudonymize-3.0.dist-info/top_level.txt
gocept.pseudonymize-3.0.dist-info/RECORD
