Metadata-Version: 2.1
Name: gocept.pseudonymize
Version: 3.0
Summary: Pseudonymize data like text, email addresses or license tags.
Home-page: https://github.com/gocept/gocept.pseudonymize
Author: gocept <mail@gocept.com>
Author-email: mail@gocept.com
License: MIT
Keywords: Pseudonymization
Classifier: Development Status :: 5 - Production/Stable
Classifier: Intended Audience :: Developers
Classifier: Intended Audience :: System Administrators
Classifier: Operating System :: OS Independent
Classifier: Topic :: Security :: Cryptography
Classifier: Topic :: Software Development :: Libraries :: Python Modules
Classifier: Topic :: Text Processing :: Filters
Classifier: Topic :: Utilities
Classifier: License :: OSI Approved :: MIT License
Classifier: Natural Language :: German
Classifier: Programming Language :: Python :: 3
Classifier: Programming Language :: Python :: 3.7
Classifier: Programming Language :: Python :: 3.8
Classifier: Programming Language :: Python :: 3.9
Classifier: Programming Language :: Python :: 3.10
Classifier: Programming Language :: Python :: 3.11
Classifier: Programming Language :: Python :: Implementation :: CPython
Requires-Python: >=3.7
License-File: LICENSE.txt
Requires-Dist: setuptools
Provides-Extra: test
Requires-Dist: mock ; extra == 'test'
